MANIFEST.in
setup.cfg
setup.py
egat/__init__.py
egat/auto_threaded_test_runner.py
egat/execution_groups.py
egat/parse.py
egat/shared_resource.py
egat/test_loader.py
egat/test_result.py
egat/test_runner_helpers.py
egat/testset.py
egat/user_threaded_test_runner.py
egat.egg-info/PKG-INFO
egat.egg-info/SOURCES.txt
egat.egg-info/dependency_links.txt
egat.egg-info/entry_points.txt
egat.egg-info/top_level.txt
egat/data/default.css
egat/data/egat_header.png
egat/loggers/__init__.py
egat/loggers/html_logger.py
egat/loggers/simple_text_logger.py
egat/loggers/test_logger.py
egat/scripts/__init__.py
egat/scripts/egatest.py