Metadata-Version: 1.1
Name: egat
Version: 1.0.0
Summary: An automated testing toolkit
Home-page: https://github.com/egineering-llc/egat
Author: E-gineering LLC
Author-email: eg.pypi@e-gineering.com
License: UNKNOWN
Download-URL: https://github.com/egineering-llc/egat/tarball/1.0.0
Keywords: testing,automated testing,functional testing
Platform: UNKNOWN
